{"paths": {"admin/js/vendor/select2/i18n/af.js": "admin\\js\\vendor\\select2\\i18n\\af.4f6fcd73488c.js", "admin/js/vendor/select2/i18n/ar.js": "admin\\js\\vendor\\select2\\i18n\\ar.65aa8e36bf5d.js", "admin/js/vendor/select2/i18n/az.js": "admin\\js\\vendor\\select2\\i18n\\az.270c257daf81.js", "admin/js/vendor/select2/i18n/bg.js": "admin\\js\\vendor\\select2\\i18n\\bg.39b8be30d4f0.js", "admin/js/vendor/select2/i18n/bn.js": "admin\\js\\vendor\\select2\\i18n\\bn.6d42b4dd5665.js", "admin/js/vendor/select2/i18n/bs.js": "admin\\js\\vendor\\select2\\i18n\\bs.91624382358e.js", "admin/js/vendor/select2/i18n/ca.js": "admin\\js\\vendor\\select2\\i18n\\ca.a166b745933a.js", "admin/js/vendor/select2/i18n/cs.js": "admin\\js\\vendor\\select2\\i18n\\cs.4f43e8e7d33a.js", "admin/js/vendor/select2/i18n/da.js": "admin\\js\\vendor\\select2\\i18n\\da.766346afe4dd.js", "admin/js/vendor/select2/i18n/de.js": "admin\\js\\vendor\\select2\\i18n\\de.8a1c222b0204.js", "admin/js/vendor/select2/i18n/dsb.js": "admin\\js\\vendor\\select2\\i18n\\dsb.56372c92d2f1.js", "admin/js/vendor/select2/i18n/el.js": "admin\\js\\vendor\\select2\\i18n\\el.27097f071856.js", "admin/js/vendor/select2/i18n/en.js": "admin\\js\\vendor\\select2\\i18n\\en.cf932ba09a98.js", "admin/js/vendor/select2/i18n/es.js": "admin\\js\\vendor\\select2\\i18n\\es.66dbc2652fb1.js", "admin/js/vendor/select2/i18n/et.js": "admin\\js\\vendor\\select2\\i18n\\et.2b96fd98289d.js", "admin/js/vendor/select2/i18n/eu.js": "admin\\js\\vendor\\select2\\i18n\\eu.adfe5c97b72c.js", "admin/js/vendor/select2/i18n/fa.js": "admin\\js\\vendor\\select2\\i18n\\fa.3b5bd1961cfd.js", "admin/js/vendor/select2/i18n/fi.js": "admin\\js\\vendor\\select2\\i18n\\fi.614ec42aa9ba.js", "admin/js/vendor/select2/i18n/fr.js": "admin\\js\\vendor\\select2\\i18n\\fr.05e0542fcfe6.js", "admin/js/vendor/select2/i18n/gl.js": "admin\\js\\vendor\\select2\\i18n\\gl.d99b1fedaa86.js", "admin/js/vendor/select2/i18n/he.js": "admin\\js\\vendor\\select2\\i18n\\he.e420ff6cd3ed.js", "admin/js/vendor/select2/i18n/hi.js": "admin\\js\\vendor\\select2\\i18n\\hi.70640d41628f.js", "admin/js/vendor/select2/i18n/hr.js": "admin\\js\\vendor\\select2\\i18n\\hr.a2b092cc1147.js", "admin/js/vendor/select2/i18n/hsb.js": "admin\\js\\vendor\\select2\\i18n\\hsb.fa3b55265efe.js", "admin/js/vendor/select2/i18n/hu.js": "admin\\js\\vendor\\select2\\i18n\\hu.6ec6039cb8a3.js", "admin/js/vendor/select2/i18n/hy.js": "admin\\js\\vendor\\select2\\i18n\\hy.c7babaeef5a6.js", "admin/js/vendor/select2/i18n/id.js": "admin\\js\\vendor\\select2\\i18n\\id.04debded514d.js", "admin/js/vendor/select2/i18n/is.js": "admin\\js\\vendor\\select2\\i18n\\is.3ddd9a6a97e9.js", "admin/js/vendor/select2/i18n/it.js": "admin\\js\\vendor\\select2\\i18n\\it.be4fe8d365b5.js", "admin/js/vendor/select2/i18n/ja.js": "admin\\js\\vendor\\select2\\i18n\\ja.170ae885d74f.js", "admin/js/vendor/select2/i18n/ka.js": "admin\\js\\vendor\\select2\\i18n\\ka.2083264a54f0.js", "admin/js/vendor/select2/i18n/km.js": "admin\\js\\vendor\\select2\\i18n\\km.c23089cb06ca.js", "admin/js/vendor/select2/i18n/ko.js": "admin\\js\\vendor\\select2\\i18n\\ko.e7be6c20e673.js", "admin/js/vendor/select2/i18n/lt.js": "admin\\js\\vendor\\select2\\i18n\\lt.23c7ce903300.js", "admin/js/vendor/select2/i18n/lv.js": "admin\\js\\vendor\\select2\\i18n\\lv.08e62128eac1.js", "admin/js/vendor/select2/i18n/mk.js": "admin\\js\\vendor\\select2\\i18n\\mk.dabbb9087130.js", "admin/js/vendor/select2/i18n/ms.js": "admin\\js\\vendor\\select2\\i18n\\ms.4ba82c9a51ce.js", "admin/js/vendor/select2/i18n/nb.js": "admin\\js\\vendor\\select2\\i18n\\nb.da2fce143f27.js", "admin/js/vendor/select2/i18n/ne.js": "admin\\js\\vendor\\select2\\i18n\\ne.3d79fd3f08db.js", "admin/js/vendor/select2/i18n/nl.js": "admin\\js\\vendor\\select2\\i18n\\nl.997868a37ed8.js", "admin/js/vendor/select2/i18n/pl.js": "admin\\js\\vendor\\select2\\i18n\\pl.6031b4f16452.js", "admin/js/vendor/select2/i18n/ps.js": "admin\\js\\vendor\\select2\\i18n\\ps.38dfa47af9e0.js", "admin/js/vendor/select2/i18n/pt-BR.js": "admin\\js\\vendor\\select2\\i18n\\pt-BR.e1b294433e7f.js", "admin/js/vendor/select2/i18n/pt.js": "admin\\js\\vendor\\select2\\i18n\\pt.33b4a3b44d43.js", "admin/js/vendor/select2/i18n/ro.js": "admin\\js\\vendor\\select2\\i18n\\ro.f75cb460ec3b.js", "admin/js/vendor/select2/i18n/ru.js": "admin\\js\\vendor\\select2\\i18n\\ru.934aa95f5b5f.js", "admin/js/vendor/select2/i18n/sk.js": "admin\\js\\vendor\\select2\\i18n\\sk.33d02cef8d11.js", "admin/js/vendor/select2/i18n/sl.js": "admin\\js\\vendor\\select2\\i18n\\sl.131a78bc0752.js", "admin/js/vendor/select2/i18n/sq.js": "admin\\js\\vendor\\select2\\i18n\\sq.5636b60d29c9.js", "admin/js/vendor/select2/i18n/sr-Cyrl.js": "admin\\js\\vendor\\select2\\i18n\\sr-Cyrl.f254bb8c4c7c.js", "admin/js/vendor/select2/i18n/sr.js": "admin\\js\\vendor\\select2\\i18n\\sr.5ed85a48f483.js", "admin/js/vendor/select2/i18n/sv.js": "admin\\js\\vendor\\select2\\i18n\\sv.7a9c2f71e777.js", "admin/js/vendor/select2/i18n/th.js": "admin\\js\\vendor\\select2\\i18n\\th.f38c20b0221b.js", "admin/js/vendor/select2/i18n/tk.js": "admin\\js\\vendor\\select2\\i18n\\tk.7c572a68c78f.js", "admin/js/vendor/select2/i18n/tr.js": "admin\\js\\vendor\\select2\\i18n\\tr.b5a0643d1545.js", "admin/js/vendor/select2/i18n/uk.js": "admin\\js\\vendor\\select2\\i18n\\uk.8cede7f4803c.js", "admin/js/vendor/select2/i18n/vi.js": "admin\\js\\vendor\\select2\\i18n\\vi.097a5b75b3e1.js", "admin/js/vendor/select2/i18n/zh-CN.js": "admin\\js\\vendor\\select2\\i18n\\zh-CN.2cff662ec5f9.js", "admin/js/vendor/select2/i18n/zh-TW.js": "admin\\js\\vendor\\select2\\i18n\\zh-TW.04554a227c2b.js", "admin/css/vendor/select2/LICENSE-SELECT2.md": "admin\\css\\vendor\\select2\\LICENSE-SELECT2.f94142512c91.md", "admin/css/vendor/select2/select2.css": "admin/css/vendor/select2/select2.a2194c262648.css", "admin/css/vendor/select2/select2.min.css": "admin/css/vendor/select2/select2.min.9f54e6414f87.css", "admin/js/vendor/jquery/jquery.js": "admin\\js\\vendor\\jquery\\jquery.23c7c5d2d131.js", "admin/js/vendor/jquery/jquery.min.js": "admin\\js\\vendor\\jquery\\jquery.min.dc5e7f18c8d3.js", "admin/js/vendor/jquery/LICENSE.txt": "admin\\js\\vendor\\jquery\\LICENSE.75308107741f.txt", "admin/js/vendor/select2/LICENSE.md": "admin\\js\\vendor\\select2\\LICENSE.f94142512c91.md", "admin/js/vendor/select2/select2.full.js": "admin\\js\\vendor\\select2\\select2.full.c2afdeda3058.js", "admin/js/vendor/select2/select2.full.min.js": "admin\\js\\vendor\\select2\\select2.full.min.fcd7500d8e13.js", "admin/js/vendor/xregexp/LICENSE.txt": "admin\\js\\vendor\\xregexp\\LICENSE.bf79e414957a.txt", "admin/js/vendor/xregexp/xregexp.js": "admin\\js\\vendor\\xregexp\\xregexp.efda034b9537.js", "admin/js/vendor/xregexp/xregexp.min.js": "admin\\js\\vendor\\xregexp\\xregexp.min.b0439563a5d3.js", "admin/img/gis/move_vertex_off.svg": "admin\\img\\gis\\move_vertex_off.7a23bf31ef8a.svg", "admin/img/gis/move_vertex_on.svg": "admin\\img\\gis\\move_vertex_on.0047eba25b67.svg", "admin/js/admin/DateTimeShortcuts.js": "admin\\js\\admin\\DateTimeShortcuts.29d0b1965c07.js", "admin/js/admin/RelatedObjectLookups.js": "admin\\js\\admin\\RelatedObjectLookups.d7e023e6523b.js", "css/images/2134701882-01.jpeg": "css\\images\\2134701882-01.99ec18f8e9f0.jpeg", "css/images/53e7d3414b52a814f6da8c7dda793678153bdee757596c48732f7dd5904bc45abc_1280.jpg": "css\\images\\53e7d3414b52a814f6da8c7dda793678153bdee757596c48732f7dd5904bc45abc_1280.abcd6cb86418.jpg", "css/images/default-image.jpg": "css\\images\\default-image.4e0232477a61.jpg", "css/images/GAMESEARCH.png": "css\\images\\GAMESEARCH.45928958eb4d.png", "css/images/GAMESEARCH2.png": "css\\images\\GAMESEARCH2.86c692062a7e.png", "css/images/pexelsphoto2473183.jpg": "css\\images\\pexelsphoto2473183.390efdea9ee6.jpg", "admin/css/autocomplete.css": "admin/css/autocomplete.781713f30664.css", "admin/css/base.css": "admin/css/base.efb520c4bb7c.css", "admin/css/changelists.css": "admin/css/changelists.69c2d200e2cb.css", "admin/css/dashboard.css": "admin/css/dashboard.be83f13e4369.css", "admin/css/fonts.css": "admin/css/fonts.168bab448fee.css", "admin/css/forms.css": "admin/css/forms.6230fc2a74ac.css", "admin/css/login.css": "admin/css/login.d2a477e04949.css", "admin/css/nav_sidebar.css": "admin/css/nav_sidebar.59831780a474.css", "admin/css/responsive.css": "admin/css/responsive.1c318745d30f.css", "admin/css/responsive_rtl.css": "admin/css/responsive_rtl.e13ae754cceb.css", "admin/css/rtl.css": "admin/css/rtl.775b89eb85cb.css", "admin/css/widgets.css": "admin/css/widgets.b12c020d05e0.css", "admin/fonts/LICENSE.txt": "admin\\fonts\\LICENSE.d273d63619c9.txt", "admin/fonts/README.txt": "admin\\fonts\\README.ab99e6b541ea.txt", "admin/fonts/Roboto-Bold-webfont.woff": "admin\\fonts\\Roboto-Bold-webfont.50d75e48e0a3.woff", "admin/fonts/Roboto-Light-webfont.woff": "admin\\fonts\\Roboto-Light-webfont.c73eb1ceba33.woff", "admin/fonts/Roboto-Regular-webfont.woff": "admin\\fonts\\Roboto-Regular-webfont.35b07eb2f871.woff", "admin/img/calendar-icons.svg": "admin\\img\\calendar-icons.39b290681a8b.svg", "admin/img/icon-addlink.svg": "admin\\img\\icon-addlink.d519b3bab011.svg", "admin/img/icon-alert.svg": "admin\\img\\icon-alert.034cc7d8a67f.svg", "admin/img/icon-calendar.svg": "admin\\img\\icon-calendar.ac7aea671bea.svg", "admin/img/icon-changelink.svg": "admin\\img\\icon-changelink.18d2fd706348.svg", "admin/img/icon-clock.svg": "admin\\img\\icon-clock.e1d4dfac3f2b.svg", "admin/img/icon-deletelink.svg": "admin\\img\\icon-deletelink.564ef9dc3854.svg", "admin/img/icon-no.svg": "admin\\img\\icon-no.439e821418cd.svg", "admin/img/icon-unknown-alt.svg": "admin\\img\\icon-unknown-alt.81536e128bb6.svg", "admin/img/icon-unknown.svg": "admin\\img\\icon-unknown.a18cb4398978.svg", "admin/img/icon-viewlink.svg": "admin\\img\\icon-viewlink.41eb31f7826e.svg", "admin/img/icon-yes.svg": "admin\\img\\icon-yes.d2f9f035226a.svg", "admin/img/inline-delete.svg": "admin\\img\\inline-delete.fec1b761f254.svg", "admin/img/LICENSE": "admin\\img\\LICENSE.2c54f4e1ca1c", "admin/img/README.txt": "admin\\img\\README.a70711a38d87.txt", "admin/img/search.svg": "admin\\img\\search.7cf54ff789c6.svg", "admin/img/selector-icons.svg": "admin\\img\\selector-icons.b4555096cea2.svg", "admin/img/sorting-icons.svg": "admin\\img\\sorting-icons.3a097b59f104.svg", "admin/img/tooltag-add.svg": "admin\\img\\tooltag-add.e59d620a9742.svg", "admin/img/tooltag-arrowright.svg": "admin\\img\\tooltag-arrowright.bbfb788a849e.svg", "admin/js/actions.js": "admin\\js\\actions.9fe89b71cbba.js", "admin/js/actions.min.js": "admin\\js\\actions.min.5f3040a29159.js", "admin/js/autocomplete.js": "admin\\js\\autocomplete.618a7ebf39d8.js", "admin/js/calendar.js": "admin\\js\\calendar.b4dcf6f850fe.js", "admin/js/cancel.js": "admin\\js\\cancel.50e7573ea4a7.js", "admin/js/change_form.js": "admin\\js\\change_form.9d8ca4f96b75.js", "admin/js/collapse.js": "admin\\js\\collapse.f84e7410290f.js", "admin/js/collapse.min.js": "admin\\js\\collapse.min.10ac29832e2c.js", "admin/js/core.js": "admin\\js\\core.fae39a43def0.js", "admin/js/inlines.js": "admin\\js\\inlines.7596b7fd289e.js", "admin/js/inlines.min.js": "admin\\js\\inlines.min.599e296e4c24.js", "admin/js/jquery.init.js": "admin\\js\\jquery.init.b7781a0897fc.js", "admin/js/nav_sidebar.js": "admin\\js\\nav_sidebar.7605597ddf52.js", "admin/js/popup_response.js": "admin\\js\\popup_response.c6cc78ea5551.js", "admin/js/prepopulate.js": "admin\\js\\prepopulate.bd2361dfd64d.js", "admin/js/prepopulate.min.js": "admin\\js\\prepopulate.min.5f7f80162256.js", "admin/js/prepopulate_init.js": "admin\\js\\prepopulate_init.e056047b7a7e.js", "admin/js/SelectBox.js": "admin\\js\\SelectBox.46d59670a7a7.js", "admin/js/SelectFilter2.js": "admin\\js\\SelectFilter2.d250dcb52a9a.js", "admin/js/urlify.js": "admin\\js\\urlify.3cabcb7a9073.js", "css/GardenSnakes.css": "css/GardenSnakes.948c9291c244.css", "css/More.css": "css/More.259cf25e2cf8.css", "css/nicepage.css": "css/nicepage.501fd3851473.css", "img/53e7d3414b52a814f6da8c7dda793678153bdee757596c48732f7dd5904bc45abc_1280.jpg": "img\\53e7d3414b52a814f6da8c7dda793678153bdee757596c48732f7dd5904bc45abc_1280.abcd6cb86418.jpg", "img/A Way Out.png": "img\\A Way Out.657ba3a03f8a.png", "img/Age of Empires II The Age of Kings.png": "img\\Age of Empires II The Age of Kings.f803c82168e4.png", "img/Baldur's Gate II Shadows of Amn.png": "img\\Baldur's Gate II Shadows of Amn.5468324a6dd0.png", "img/Baldur's Gate III.png": "img\\Baldur's Gate III.1dc53d5c02bb.png", "img/Baldur's Gate.png": "img\\Baldur's Gate.1850fb4e143c.png", "img/Batman Arkham Asylum.png": "img\\Batman Arkham Asylum.07574b61dff2.png", "img/Batman Arkham City.png": "img\\Batman Arkham City.a863c6e304cb.png", "img/Battlefield 2.png": "img\\Battlefield 2.63561b474afd.png", "img/Battlefield 3.png": "img\\Battlefield 3.492f5499c043.png", "img/Battlefield 4.png": "img\\Battlefield 4.6ff0d51539dc.png", "img/Battlefield Hardline.png": "img\\Battlefield Hardline.1d36c4c874be.png", "img/Battlefield V.png": "img\\Battlefield V.657dd1592fa6.png", "img/Battlefield.png": "img\\Battlefield.3ead40b36aec.png", "img/BioShock Infinite.png": "img\\BioShock Infinite.8fd680eb88c9.png", "img/BioShock.png": "img\\BioShock.88d854019062.png", "img/Black & White.png": "img\\Black & White.81ee37cd12e2.png", "img/Burnout Paradise Remastered.png": "img\\Burnout Paradise Remastered.2a93f77e16ba.png", "img/Call of Duty 4 Modern Warfare.png": "img\\Call of Duty 4 Modern Warfare.47118489d32d.png", "img/Call of Duty.png": "img\\Call of Duty.c4f6e873a50b.png", "img/Company of Heroes.png": "img\\Company of Heroes.edbe6c7f635f.png", "img/Crusader Kings III.png": "img\\Crusader Kings III.a7593394d424.png", "img/Crysis.png": "img\\Crysis.3dd7ed1913f5.png", "img/Dark Souls II.png": "img\\Dark Souls II.0ee98425b8f5.png", "img/Dead Space 2.png": "img\\Dead Space 2.ed239431434f.png", "img/Dead Space 3.png": "img\\Dead Space 3.6773a83cda96.png", "img/Dead Space.png": "img\\Dead Space.8754c553cfe9.png", "img/default-image.jpg": "img\\default-image.4e0232477a61.jpg", "img/Deus E.png": "img\\Deus E.3603de4d5e0a.png", "img/Diablo.png": "img\\Diablo.832f4c9e8ef0.png", "img/Disco Elysium.png": "img\\Disco Elysium.cf1a2e01bac7.png", "img/Dishonored.png": "img\\Dishonored.e5d7dc12fa7d.png", "img/Divinity Original Sin II.png": "img\\Divinity Original Sin II.00ec295b71a9.png", "img/Dragon Age II.png": "img\\Dragon Age II.ea512921e132.png", "img/Dragon Age Inquisition.png": "img\\Dragon Age Inquisition.d3161c032b11.png", "img/Dragon Age Origins.png": "img\\Dragon Age Origins.13e6f1a50634.png", "img/Fallout 3.png": "img\\Fallout 3.0fea5af3a04d.png", "img/Fe.png": "img\\Fe.36c52a2d094e.png", "img/Fez.png": "img\\Fez.4e26b1e16ce8.png", "img/Final Fantasy XIV Shadowbringers.png": "img\\Final Fantasy XIV Shadowbringers.7ad3fcc5bf36.png", "img/FreeSpace 2.png": "img\\FreeSpace 2.3109e0a561d0.png", "img/Galactic Civilizations II Dark Avatar.png": "img\\Galactic Civilizations II Dark Avatar.7097704ac33e.png", "img/Galactic Civilizations II Twilight of the Arnor.png": "img\\Galactic Civilizations II Twilight of the Arnor.bc3155aaac72.png", "img/GAMESEARCH.png": "img\\GAMESEARCH.45928958eb4d.png", "img/GAMESEARCH2.png": "img\\GAMESEARCH2.86c692062a7e.png", "img/GameSearchIcon.png": "img\\GameSearchIcon.6db9a2ce2a0a.png", "img/Grand Theft Auto III.png": "img\\Grand Theft Auto III.cdcab4aca5ab.png", "img/Grand Theft Auto San Andreas.png": "img\\Grand Theft Auto San Andreas.c3edcd1b8542.png", "img/Grand Theft Auto V.png": "img\\Grand Theft Auto V.1bcbf558bef0.png", "img/Grand Theft Auto Vice City.png": "img\\Grand Theft Auto Vice City.73ee7c5d0bee.png", "img/Grim Fandango.png": "img\\Grim Fandango.941a1212867a.png", "img/Hades.png": "img\\Hades.0cd4a8c61cda.png", "img/Half-Life 2.png": "img\\Half-Life 2.a07afac2033c.png", "img/Half-Life Alyx.png": "img\\Half-Life Alyx.559d5752e81e.png", "img/Half-Life.png": "img\\Half-Life.00b8966c492c.png", "img/Homeworld.png": "img\\Homeworld.b293ce4a6799.png", "img/IL-2 Sturmovik.png": "img\\IL-2 Sturmovik.2cca7ee9333b.png", "img/Jade Empire Special Edition.png": "img\\Jade Empire Special Edition.df7c1d2cb054.png", "img/Kentucky Route Zero - Act III.png": "img\\Kentucky Route Zero - Act III.af87af62c365.png", "img/Madden NFL 2004.png": "img\\Madden NFL 2004.cc41dd3092db.png", "img/Mark of the Ninja.png": "img\\Mark of the Ninja.61eab50db2e2.png", "img/Mass Effect 2.png": "img\\Mass Effect 2.59d3ef194257.png", "img/Mass Effect 3.png": "img\\Mass Effect 3.793ae772e6d4.png", "img/Mass Effect Andromeda.png": "img\\Mass Effect Andromeda.13010def1523.png", "img/Mass Effect.png": "img\\Mass Effect.70c25551888a.png", "img/Medal of Honor (2010).png": "img\\Medal of Honor (2010).10185a7b9c69.png", "img/Medal of Honor Airborne.png": "img\\Medal of Honor Airborne.bff8716efc7e.png", "img/Medal of Honor Allied Assault.png": "img\\Medal of Honor Allied Assault.0f5225276310.png", "img/Metal Gear Solid V The Phantom Pain.png": "img\\Metal Gear Solid V The Phantom Pain.8bdeb2fd8fc8.png", "img/Microsoft Flight Simulator.png": "img\\Microsoft Flight Simulator.53d5b9e64b61.png", "img/Minecraft.png": "img\\Minecraft.ec71739a78f6.png", "img/Mirror's Edge Catalyst.png": "img\\Mirror's Edge Catalyst.038a30c59f81.png", "img/Mirror's Edge.png": "img\\Mirror's Edge.2e20e1301077.png", "img/Myth The Fallen Lords.png": "img\\Myth The Fallen Lords.1e27afa86f15.png", "img/Need for Speed Heat.png": "img\\Need for Speed Heat.77a551b4da0d.png", "img/Need for Speed Payback.png": "img\\Need for Speed Payback.959382d06cc7.png", "img/Need for Speed Rivals.png": "img\\Need for Speed Rivals.d06294796525.png", "img/Need for Speed.png": "img\\Need for Speed.4fc6011b09ff.png", "img/Neverwinter Nights.png": "img\\Neverwinter Nights.60f148ac03b8.png", "img/NHL 2001.png": "img\\NHL 2001.36c486c1d6d5.png", "img/No One Lives Forever 2 A Spy in H.A.R.M.'s Way.png": "img\\No One Lives Forever 2 A Spy in H.A.R.M.'s Way.760e6ff13ec9.png", "img/Okami HD.png": "img\\Okami HD.82775052ed34.png", "img/Overwatch.png": "img\\Overwatch.00ef515e61e8.png", "img/Peggl.png": "img\\Peggl.a91c7408bb0d.png", "img/Peggle Nights.png": "img\\Peggle Nights.9014492c3f4f.png", "img/Peggle.png": "img\\Peggle.a91c7408bb0d.png", "img/pexelsphoto2473183.jpg": "img\\pexelsphoto2473183.390efdea9ee6.jpg", "img/Planescape Torment.png": "img\\Planescape Torment.b5f997c701d2.png", "img/Plants vs. Zombies.png": "img\\Plants vs. Zombies.fb5a809d4ee3.png", "img/Portal 2.png": "img\\Portal 2.c5ece2aa1007.png", "img/Portal.png": "img\\Portal.67773cfff0c4.png", "img/Quake.png": "img\\Quake.f09872f29ba7.png", "img/Red Dead Redemption 2.png": "img\\Red Dead Redemption 2.6e1366e985d3.png", "img/Rome Total War.png": "img\\Rome Total War.9d13a2c9230c.png", "img/Sea of Solitude.png": "img\\Sea of Solitude.72ca7bfbb2c4.png", "img/Sekiro Shadows Die Twice.png": "img\\Sekiro Shadows Die Twice.3a7aee583784.png", "img/Sid Meier's Alpha Centauri.png": "img\\Sid Meier's Alpha Centauri.37b9ff312cd0.png", "img/Sid Meier's Civilization II.png": "img\\Sid Meier's Civilization II.58f089fad415.png", "img/Sid Meier's Civilization IV.png": "img\\Sid Meier's Civilization IV.962a160649c9.png", "img/Sid Meier's Gettysburg!.png": "img\\Sid Meier's Gettysburg!.e66a08fd2e56.png", "img/SimCity 4.png": "img\\SimCity 4.aa2d62066c30.png", "img/Sims 4.png": "img\\Sims 4.7dd64f4fb94d.png", "img/Sims City 4.png": "img\\Sims City 4.aa2d62066c30.png", "img/Spelunky 2.png": "img\\Spelunky 2.ed114fd00294.png", "img/Spelunky.png": "img\\Spelunky.897cf53f4900.png", "img/Spore.png": "img\\Spore.7015ef3e2b7f.png", "img/Star Wars Battlefront II .png": "img\\Star Wars Battlefront II .2e348568aee8.png", "img/Star Wars Battlefront.png": "img\\Star Wars Battlefront.e740ed36fe6f.png", "img/Star Wars Jedi Fallen Order.png": "img\\Star Wars Jedi Fallen Order.8888f8dc4287.png", "img/Star Wars Jedi Knight Dark Forces II.png": "img\\Star Wars Jedi Knight Dark Forces II.e7eb8bc8befc.png", "img/Star Wars Knights of the Old Republic.png": "img\\Star Wars Knights of the Old Republic.86a9bbb562d5.png", "img/Starcraft II Wings of Liberty.png": "img\\Starcraft II Wings of Liberty.d3441bb67476.png", "img/Stephen's Sausage Roll.png": "img\\Stephen's Sausage Roll.b981f5df8dff.png", "img/Street Fighter IV.png": "img\\Street Fighter IV.150965db6418.png", "img/System Shock 2.png": "img\\System Shock 2.567be794c23a.png", "img/Team Fortress 2.png": "img\\Team Fortress 2.799c597163f1.png", "img/Tetris Effect.png": "img\\Tetris Effect.efb09f83a909.png", "img/The Elder Scrolls IV Oblivion.png": "img\\The Elder Scrolls IV Oblivion.a1aed1724b4c.png", "img/The Elder Scrolls V Skyrim.png": "img\\The Elder Scrolls V Skyrim.ddbafbf43a08.png", "img/The Longest Journey.png": "img\\The Longest Journey.82b941547dc6.png", "img/The Operative No One Lives Forever.png": "img\\The Operative No One Lives Forever.9d4a36e39a05.png", "img/The Orange Box.png": "img\\The Orange Box.0e1774a19133.png", "img/The Sims 2.png": "img\\The Sims 2.5b0482861659.png", "img/The Sims 3.png": "img\\The Sims 3.4f1272e58a47.png", "img/The Sims 4.png": "img\\The Sims 4.7dd64f4fb94d.png", "img/The Sims.png": "img\\The Sims.08f817cf8023.png", "img/The Witcher 3 Wild Hunt - Blood and Wine.png": "img\\The Witcher 3 Wild Hunt - Blood and Wine.bf820208a5c8.png", "img/The Witcher 3 Wild Hunt.png": "img\\The Witcher 3 Wild Hunt.2af19c101b15.png", "img/Thief The Dark Project.png": "img\\Thief The Dark Project.59df4057d3af.png", "img/Tiger Woods PGA Tour 2003.png": "img\\Tiger Woods PGA Tour 2003.457311257c6d.png", "img/Tiger Woods PGA Tour 2005.png": "img\\Tiger Woods PGA Tour 2005.413fa745e282.png", "img/Titanfall 2.png": "img\\Titanfall 2.a82596e445c2.png", "img/Tom Clancy's Splinter Cell Chaos Theory.png": "img\\Tom Clancy's Splinter Cell Chaos Theory.7185c5ff948d.png", "img/Tom Clancy's Splinter Cell.png": "img\\Tom Clancy's Splinter Cell.9a7e561597ce.png", "img/Tony Hawk's Pro Skater 2.png": "img\\Tony Hawk's Pro Skater 2.25f9085129f2.png", "img/Tony Hawk's Pro Skater 3.png": "img\\Tony Hawk's Pro Skater 3.d0faf95b8cb2.png", "img/Undertale.png": "img\\Undertale.1cfafc60685c.png", "img/Unravel Two.png": "img\\Unravel Two.ccdb89ad4b1a.png", "img/Unravel.png": "img\\Unravel.36ed97632418.png", "img/Unreal Tournament (1999).png": "img\\Unreal Tournament (1999).4ba9b377da08.png", "img/Unreal Tournament 2004.png": "img\\Unreal Tournament 2004.dc251d3933b5.png", "img/Warcraft III Reign of Chaos.png": "img\\Warcraft III Reign of Chaos.8b11cebaf20a.png", "img/World of Goo.png": "img\\World of Goo.a9d012a3f20b.png", "img/World of Warcraft Cataclysm.png": "img\\World of Warcraft Cataclysm.cdee8d33aa6b.png", "img/World of Warcraft The Burning Crusade.png": "img\\World of Warcraft The Burning Crusade.0ef259a49908.png", "img/World of Warcraft Wrath of the Lich King.png": "img\\World of Warcraft Wrath of the Lich King.a86e957b995b.png", "img/World of Warcraft.png": "img\\World of Warcraft.ad3a5fd2cee5.png", "img/World Soccer Winning Eleven 7 International.png": "img\\World Soccer Winning Eleven 7 International.62847f647c31.png", "js/jquery.js": "js\\jquery.f9c85864c93a.js", "js/nicepage.js": "js\\nicepage.10120ce17d2b.js"}, "version": "1.0"}